{
  "status": "OK",
  "copyright": "Copyright (c) 2024 Pro Publica Inc. All Rights Reserved.",
  "results": [
    {
      "first_member_id": "B001308",
      "first_member_api_uri": "https://api.propublica.org/congress/v1/members/B001308.json",
      "second_member_id": "C001094",
      "second_member_api_uri": "https://api.propublica.org/congress/v1/members/C001094.json",
      "congress": "116",
      "chamber": "House",
      "common_votes": 886,
      "disagree_votes": 470,
      "agree_percent": 0.47,
      "disagree_percent": 0.53
    }
  ]
}