{
  "status": "OK",
  "copyright": "Copyright (c) 2024 Pro Publica Inc. All Rights Reserved.",
  "results": [
    {
      "congress": "115",
      "bill_id": "hr3946-115",
      "num_results": 2,
      "offset": 0,
      "amendments": [
        {
          "amendment_number": "S.AMDT.4064",
          "slug": "samdt4064",
          "sponsor_title": "Sen.",
          "sponsor": "Johnny Isakson",
          "sponsor_id": "I000055",
          "sponsor_uri": "https://api.propublica.org/congress/v1/members/I000055.json",
          "sponsor_party": "R",
          "sponsor_state": "GA",
          "introduced_date": "2018-11-27",
          "title": "To amend the title.",
          "congressdotgov_url": "https://www.congress.gov/amendment/115th-congress/senate-amendment/4064/text",
          "latest_major_action_date": "2018-11-27",
          "latest_major_action": "Amendment SA 4064 agreed to in Senate by Unanimous Consent."
        }
      ]
    }
  ]
}